<Ui xmlns="http://www.blizzard.com/wow/ui/"
	xmlns:xsi="http://www.w3.org/2001/XMLSchema-instance"
	xsi:schemaLocation="http://www.blizzard.com/wow/ui/ ..\FrameXML\UI.xsd">
	<Frame name="BottomFrame" toplevel="true" parent="UIParent" frameStrata="MEDIUM">
		<Size>
			<AbsDimension x="1600" y="200"/>
		</Size>
		<Anchors>
			<Anchor point="BOTTOM"/>
		</Anchors>
		<Backdrop bgFile="Interface\Tooltips\UI-Tooltip-Background">
			<Color r="0" g="0" b="0" a="1"/>
		</Backdrop>
		<Scripts>
			<OnLoad>
				BottomFrame_OnLoad();
			</OnLoad>
		</Scripts>
	</Frame>
</Ui>
